ShiyanlouLinuxJiaochengHeji20160904Fix1/README.md
ShiyanlouLinuxJiaochengHeji20160904Fix1/__init__.py
ShiyanlouLinuxJiaochengHeji20160904Fix1/__main__.py
ShiyanlouLinuxJiaochengHeji20160904Fix1/file.epub
ShiyanlouLinuxJiaochengHeji20160904Fix1/index.html
ShiyanlouLinuxJiaochengHeji20160904Fix1/css/__init__.py
ShiyanlouLinuxJiaochengHeji20160904Fix1/css/annotations.css
ShiyanlouLinuxJiaochengHeji20160904Fix1/css/main.css
ShiyanlouLinuxJiaochengHeji20160904Fix1/css/normalize.css
ShiyanlouLinuxJiaochengHeji20160904Fix1/css/popup.css
ShiyanlouLinuxJiaochengHeji20160904Fix1/font/__init__.py
ShiyanlouLinuxJiaochengHeji20160904Fix1/font/fontello.eot
ShiyanlouLinuxJiaochengHeji20160904Fix1/font/fontello.svg
ShiyanlouLinuxJiaochengHeji20160904Fix1/font/fontello.ttf
ShiyanlouLinuxJiaochengHeji20160904Fix1/font/fontello.woff
ShiyanlouLinuxJiaochengHeji20160904Fix1/img/__init__.py
ShiyanlouLinuxJiaochengHeji20160904Fix1/img/annotator-glyph-sprite.png
ShiyanlouLinuxJiaochengHeji20160904Fix1/img/annotator-icon-sprite.png
ShiyanlouLinuxJiaochengHeji20160904Fix1/img/apple-touch-icon.png
ShiyanlouLinuxJiaochengHeji20160904Fix1/img/cancelfullscreen.png
ShiyanlouLinuxJiaochengHeji20160904Fix1/img/close.png
ShiyanlouLinuxJiaochengHeji20160904Fix1/img/fullscreen.png
ShiyanlouLinuxJiaochengHeji20160904Fix1/img/loader.gif
ShiyanlouLinuxJiaochengHeji20160904Fix1/img/menu-icon.png
ShiyanlouLinuxJiaochengHeji20160904Fix1/img/save.png
ShiyanlouLinuxJiaochengHeji20160904Fix1/img/saved.png
ShiyanlouLinuxJiaochengHeji20160904Fix1/img/settings-s.png
ShiyanlouLinuxJiaochengHeji20160904Fix1/img/settings.png
ShiyanlouLinuxJiaochengHeji20160904Fix1/img/star.png
ShiyanlouLinuxJiaochengHeji20160904Fix1/js/__init__.py
ShiyanlouLinuxJiaochengHeji20160904Fix1/js/epub.js
ShiyanlouLinuxJiaochengHeji20160904Fix1/js/epub.min.js
ShiyanlouLinuxJiaochengHeji20160904Fix1/js/epub.min.map
ShiyanlouLinuxJiaochengHeji20160904Fix1/js/hooks.min.js
ShiyanlouLinuxJiaochengHeji20160904Fix1/js/hooks.min.map
shiyanlou_linux_jiaocheng_heji_20160904_fix1-2024.3.2.0.dist-info/METADATA
shiyanlou_linux_jiaocheng_heji_20160904_fix1-2024.3.2.0.dist-info/WHEEL
shiyanlou_linux_jiaocheng_heji_20160904_fix1-2024.3.2.0.dist-info/entry_points.txt
shiyanlou_linux_jiaocheng_heji_20160904_fix1-2024.3.2.0.dist-info/top_level.txt
shiyanlou_linux_jiaocheng_heji_20160904_fix1-2024.3.2.0.dist-info/RECORD
